{
  "id": "WM_012",
  "moment_id": "WM_012",
  "incident_id": "INC_SEALED_LETTER",
  "title": "The Sealed Letter",
  "subtitle": "Chapter 02 · The Wider Fractures",
  "introduction": "A quiet study desk has letters, candle wax, and a wax seal stamp. Focus on the red wax seal.",
  "description": "A sealed letter sits on the table. A copper envelope opener slides near the paper, but the message text appears on the folded sheet exactly two seconds before the wax seal is broken.",
  "observation": "The internal text of the letter aligns and reads clearly while the outer red wax seal is completely unbroken.",
  "reconstruction": "Carry the red wax seal, the copper opener, and the folded sheet.",
  "attunements": [
    "The red wax is completely solid and unbroken, carrying no cracks.",
    "The copper blade is cold, held exactly one inch away from the paper.",
    "The ink on the inside is dry, but readable through the sealed paper."
  ],
  "revelation": "What was wrong: the message was read and registered before the envelope could be opened.\n\nWhy it mattered: the sender's intentions were already fully known to the receiver, bypassing the physical envelope entirely.",
  "background": "res://assets/witness/wm_001_studio_background.png",
  "action": "res://assets/witness/wm_001_hand_action.png",
  "reveal": "res://assets/witness/wm_001_prism_reveal.png",
  "observation_duration": 2.0,
  "anomaly_definition": {
    "location": {"x": 240.0, "y": 380.0},
    "size": {"x": 105.0, "y": 105.0},
    "misstep_text": "Not there. Watch the red wax seal on the folded letter.",
    "success_text": "Cognitive pre-revelation detected. The text is readable while the seal is intact."
  },
  "capture_window": {
    "start_time": 0.55,
    "end_time": 1.00,
    "hold_duration": 0.25,
    "guidance_text": "HOLD WHEN THE WAX MOLECULES ENCOUNTER FRICTION.",
    "success_text": "Timeline isolated: text is readable while sealed."
  },
  "evidence_nodes": [
    {
      "identifier": "wax_seal",
      "location": {"x": 100.0, "y": 200.0},
      "description": "The Red Wax Seal",
      "relevance": "THE RED WAX IS SOLID AND UNBROKEN. Red candle wax holds the folds securely in place, showing no tool fractures.",
      "truth_connection": "Physical state aligned.",
      "asset_reference": "res://assets/witness/wm_001_prism_reveal.png",
      "color_modulation": "#caa385",
      "visual_effect": "glow"
    },
    {
      "identifier": "envelope_opener",
      "location": {"x": 100.0, "y": 250.0},
      "description": "The Copper Opener",
      "relevance": "THE COPPER BLADE IS COLD. The opener hangs in suspension, held one inch away from the paper folds.",
      "truth_connection": "Action path verified.",
      "asset_reference": "res://assets/witness/wm_001_prism_reveal.png",
      "color_modulation": "#caa084",
      "visual_effect": "glow"
    },
    {
      "identifier": "letter_sheet",
      "location": {"x": 100.0, "y": 300.0},
      "description": "The Folded Sheet",
      "relevance": "THE INTERNAL INK IS LEGIBLE. The text is read and processed before the seal is physically destroyed.",
      "truth_connection": "Chronology confirmed.",
      "asset_reference": "res://assets/witness/wm_001_prism_reveal.png",
      "color_modulation": "#caa88a",
      "visual_effect": "glow"
    }
  ],
  "reward_definition": {
    "base_resonance": 20,
    "accuracy_multiplier": 15.0,
    "unassisted_bonus": 6
  },
  "asset_manifest": {
    "environment_asset": "res://assets/witness/wm_001_studio_background.png",
    "background_layers": [
      "res://assets/witness/wm_001_studio_background.png"
    ],
    "evidence_assets": {
      "wax_seal": {
        "texture_path": "res://assets/witness/wm_001_prism_reveal.png",
        "color_modulation": "#caa385",
        "visual_effect": "glow"
      },
      "envelope_opener": {
        "texture_path": "res://assets/witness/wm_001_prism_reveal.png",
        "color_modulation": "#caa084",
        "visual_effect": "glow"
      },
      "letter_sheet": {
        "texture_path": "res://assets/witness/wm_001_prism_reveal.png",
        "color_modulation": "#caa88a",
        "visual_effect": "glow"
      }
    },
    "audio_assets": {
      "ambient": "res://assets/audio/wm012_ambient.ogg",
      "anomaly": "res://assets/audio/wm012_anomaly.ogg",
      "resolution": "res://assets/audio/wm012_resolution.ogg"
    },
    "visual_effects": {
      "pulse_speed": 1.2
    },
    "lighting_profile": {
      "modulate_color": "#cba084",
      "vignette_intensity": 0.52
    }
  }
}
